{
  "cli": {
    "version": ">= 5.9.0"
  },
  "build": {
    "development": {
      "distribution": "internal",
      "android": {
        "gradleCommand": ":app:assembleDebug"
      },
      "ios": {
        "buildConfiguration": "Debug"
      }
    },
    "preview": {
      "distribution": "internal",
      "android": {
        "buildType": "apk"
      },
      "env": {
        "APP_ENV": "myEnv",
        "ANDROID_SDK_ROOT": "/Users/goncearu/Library/Android/sdk",
        "ANDROID_HOME": "/Users/goncearu/Library/Android/sdk"
      }
    },
    "production": {}
  },
  "submit": {
    "production": {}
  }
}
